corpora/corppoetry_en/en.alliteration.txt
corpora/corppoetry_en/en.hopkins.txt
corpora/corppoetry_en/en.shakespeare.txt
corpora/corppoetry_en/en.test.txt
corpora/corppoetry_en/en.whitman.txt
corpora/corppoetry_en/en.yeats.early.txt
corpora/corppoetry_en/en.yeats.late.txt
corpora/corppoetry_fi/fi.erkko.txt
corpora/corppoetry_fi/fi.hellaakoski.nimettomia.txt
corpora/corppoetry_fi/fi.hellaakoski.runoja.txt
corpora/corppoetry_fi/fi.kalevala.txt
corpora/corppoetry_fi/fi.koskenniemi.txt
corpora/corppoetry_fi/fi.onerva.liesilauluja.txt
corpora/corppoetry_fi/fi.siljo.maan-puoleen.txt
corpora/corppoetry_fi/fi.siljo.teuvo-pakkala.txt
profile/profile_parsing.py
prosodic/__init__.py
prosodic/cli.py
prosodic/ents.py
prosodic/imports.py
prosodic/prosodic.py
prosodic/utils.py
prosodic/langs/__init__.py
prosodic/langs/langs.py
prosodic/langs/phonemes.json
prosodic/langs/english/__init__.py
prosodic/langs/english/ambig_stress_words.txt
prosodic/langs/english/english.py
prosodic/langs/english/english.tsv
prosodic/langs/english/unstressed_words.txt
prosodic/langs/finnish/__init__.py
prosodic/langs/finnish/compound.txt
prosodic/langs/finnish/config.txt
prosodic/langs/finnish/finnish.py
prosodic/langs/finnish/finnish_annotator.py
prosodic/langs/finnish/finnish_functions.py
prosodic/langs/finnish/finnish_sonority.py
prosodic/langs/finnish/finnish_stress.py
prosodic/langs/finnish/finnish_syllables.py
prosodic/langs/finnish/finnish_text.py
prosodic/langs/finnish/finnish_weight.py
prosodic/langs/finnish/initial.txt
prosodic/langs/finnish/presyllabified.txt
prosodic/langs/finnish/suffix.txt
prosodic/langs/finnish/unstressed.txt
prosodic/lib/MaxEnt.py
prosodic/lib/__init__.py
prosodic/lib/lexconvert.py
prosodic/lib/metricaltree/README.md
prosodic/lib/metricaltree/__init__.py
prosodic/lib/metricaltree/deptree.py
prosodic/lib/metricaltree/get-deps.sh
prosodic/lib/metricaltree/metricaltree.py
prosodic/lib/metricaltree/test.py
prosodic/lib/panphon/LICENSE.txt
prosodic/lib/panphon/README.md
prosodic-2.1.2.dist-info/LICENSE.md
prosodic-2.1.2.dist-info/METADATA
prosodic-2.1.2.dist-info/WHEEL
prosodic-2.1.2.dist-info/entry_points.txt
prosodic-2.1.2.dist-info/top_level.txt
prosodic-2.1.2.dist-info/RECORD
