Metadata-Version: 2.1
Name: prosodic
Version: 2.1.2
Summary: Prosodic 2: a metrical-phonological parser, written in Python. For English and Finnish, with flexible language support.
Author-email: Ryan Heuser <ryan.heuser@princeton.edu>
License: Apache License, Version 2.0
Project-URL: Homepage, https://github.com/quadrismegistus/prosodic/tree/develop
Project-URL: Project Home, https://prosodic.stanford.edu
Project-URL: Bug Tracker, https://github.com/quadrismegistus/prosodic/issues
Classifier: Development Status :: 2 - Pre-Alpha
Classifier: Programming Language :: Python :: 3
Classifier: Intended Audience :: Developers
Classifier: License :: OSI Approved :: Apache Software License
Classifier: Operating System :: OS Independent
Classifier: Topic :: Software Development :: Libraries :: Python Modules
Requires-Python: >=3.8
License-File: LICENSE.md
Requires-Dist: ftfy
Requires-Dist: langdetect
Requires-Dist: pandas
Requires-Dist: gruut-ipa
Requires-Dist: numpy
Requires-Dist: multiset
Requires-Dist: nltk
Requires-Dist: phonemizer
Requires-Dist: orjson
Requires-Dist: ordered-set
Requires-Dist: click
Requires-Dist: editdistance
Requires-Dist: logmap
Requires-Dist: loguru
Requires-Dist: orjson
Requires-Dist: ipython
Requires-Dist: flask
Requires-Dist: flask-socketio
Requires-Dist: gevent
Requires-Dist: gevent-websocket
Requires-Dist: scipy
Requires-Dist: unicodecsv
Requires-Dist: PyYAML
Requires-Dist: regex
Requires-Dist: editdistance
Requires-Dist: munkres
Requires-Dist: hashstash
Requires-Dist: svgling
Requires-Dist: plotnine
Provides-Extra: dev
Requires-Dist: black>=22.10.0; extra == "dev"
Requires-Dist: pre-commit>=2.20.0; extra == "dev"
Requires-Dist: tox; extra == "dev"
Requires-Dist: sphinx; extra == "dev"
Requires-Dist: twine; extra == "dev"
Requires-Dist: wheel; extra == "dev"
Requires-Dist: pytest-cov; extra == "dev"
Requires-Dist: pytest>=7.2; extra == "dev"
Requires-Dist: selenium; extra == "dev"
Requires-Dist: pytest-cov; extra == "dev"
Requires-Dist: pytest>=7.2; extra == "dev"
Provides-Extra: all
Requires-Dist: black>=22.10.0; extra == "all"
Requires-Dist: pre-commit>=2.20.0; extra == "all"
Requires-Dist: tox; extra == "all"
Requires-Dist: sphinx; extra == "all"
Requires-Dist: twine; extra == "all"
Requires-Dist: wheel; extra == "all"
Requires-Dist: pytest-cov; extra == "all"
Requires-Dist: pytest>=7.2; extra == "all"
